CREDITS.txt
INSTALL.txt
LICENSE.txt
README.txt
setup.py
doc/presentation.txt
doc/licenses/BSD.txt
src/tramline/__init__.py
src/tramline/core.py
src/tramline/interfaces.py
src/tramline/simplefilter.py
src/tramline.egg-info/PKG-INFO
src/tramline.egg-info/SOURCES.txt
src/tramline.egg-info/dependency_links.txt
src/tramline.egg-info/not-zip-safe
src/tramline.egg-info/top_level.txt
src/tramline/tests/__init__.py
src/tramline/tests/test_core.py
src/tramline/tests/data/input1.txt
src/tramline/tests/data/input2.txt
src/tramline/tests/data/input3.txt
src/tramline/tests/data/input4.txt
src/tramline/tests/data/input5.txt
