Metadata-Version: 1.0
Name: tramline
Version: 0.5.1
Summary: An easy and fast upload and download accelerator for application servers.
Home-page: http://www.infrae.com/products/tramline
Author: Martijn Faassen
Author-email: faassen@infrae.com
License: UNKNOWN
Keywords: web zope command-line skeleton project
Platform: UNKNOWN
Classifier: Development Status :: 5 - Production/Stable
Classifier: Intended Audience :: Developers
Classifier: License :: OSI Approved :: BSD License
Classifier: Programming Language :: Python
Classifier: Topic :: Internet :: WWW/HTTP
